repo_chat/__init__.py
repo_chat/chain_manager.py
repo_chat/chat_utils.py
repo_chat/eval_utils.py
repo_chat/templates.py
repo_chat-0.1.3.dist-info/METADATA
repo_chat-0.1.3.dist-info/WHEEL
repo_chat-0.1.3.dist-info/top_level.txt
repo_chat-0.1.3.dist-info/RECORD
