Metadata-Version: 2.1
Name: repo-chat
Version: 0.1.3
Summary: Using LLMS to facilitate document retrieval and chat operations
Home-page: https://github.com/voynow/repo-chat
Author: Jamie Voynow
Author-email: voynow99@gmail.com
Classifier: Programming Language :: Python :: 3
Classifier: License :: OSI Approved :: MIT License
Classifier: Operating System :: OS Independent
Requires-Python: >=3.6
Requires-Dist: langchain
Requires-Dist: pandas
Requires-Dist: matplotlib
Requires-Dist: numpy
Requires-Dist: ipywidgets
Requires-Dist: uuid
Requires-Dist: python-dotenv
Requires-Dist: git2vec
